django_auth_network_client/__init__.py
django_auth_network_client/admin.py
django_auth_network_client/apps.py
django_auth_network_client/models.py
django_auth_network_client/urls.py
django_auth_network_client/views.py
django_auth_network_client/migrations/0001_initial.py
django_auth_network_client/migrations/__init__.py
django_auth_network_client/static/css/django_auth_network_client.css
django_auth_network_client/static/js/django_auth_network_client.js
django_auth_network_client/templates/django_auth_network_client/base.html
django_auth_network_client/templates/django_auth_network_client/warn.html
django_auth_network_client-0.2.6.dist-info/METADATA
django_auth_network_client-0.2.6.dist-info/RECORD
django_auth_network_client-0.2.6.dist-info/WHEEL
django_auth_network_client-0.2.6.dist-info/top_level.txt
