Metadata-Version: 2.1
Name: django-auth-network-client
Version: 0.2.6
Summary: Django Auth Network (DAN) is a set of two packages that create Google and Facebook-style authentication, but using your own provider instead of Google or Facebook. This is the client package, and it allows an app to connect to your provider package.
Home-page: https://github.com/antoningrele/django-auth-network-client
Author: Antonin Grêlé
Author-email: antonin.grele@gmail.com
License: BSD
Keywords: django-auth-network-client
Platform: UNKNOWN
Classifier: Development Status :: 3 - Alpha
Classifier: Framework :: Django
Classifier: Framework :: Django :: 1.10
Classifier: Intended Audience :: Developers
Classifier: License :: OSI Approved :: BSD License
Classifier: Natural Language :: English
Classifier: Programming Language :: Python :: 2
Classifier: Programming Language :: Python :: 2.7
Classifier: Programming Language :: Python :: 3
Classifier: Programming Language :: Python :: 3.4
Classifier: Programming Language :: Python :: 3.5
Requires-Dist: django-model-utils (>=2.0)
